MANIFEST.in
README.md
setup.py
django_cprofile_middleware/__init__.py
django_cprofile_middleware/metadata.py
django_cprofile_middleware/middleware.py
django_cprofile_middleware/utils.py
django_cprofile_middleware.egg-info/PKG-INFO
django_cprofile_middleware.egg-info/SOURCES.txt
django_cprofile_middleware.egg-info/dependency_links.txt
django_cprofile_middleware.egg-info/top_level.txt