Metadata-Version: 2.1
Name: django-cprofile-middleware
Version: 1.0.4
Summary: Easily add cProfile profiling to django views.
Home-page: https://github.com/omarish/django-cprofile-middleware/
Author: Omar Bohsali
Author-email: me@omarish.com
License: MIT
Keywords: django,profiling,cProfile
Platform: UNKNOWN
Classifier: Framework :: Django
